{"categoria": "Mondo", "sottotitolo": "soccorsi stentano giorni dopo idai fece 1000 morti", "testo": "salito ad almeno 38 morti bilancio provvisorio ciclone kenneth \u00e8 abbattuto nord mozambico scorsa settimana ad colpire paese africano in mese dopo idai vittime se ne era lasciate dietro circa mille mozambico malawi zimbabwe giorni distanza i soccorsi stentano ad arrivare per via dei terreni alluvionati perch\u00e9 gli aeroporti chiusi i voli restano terra\u00a0\u00a0\u00a0 kenneth proveniente dalle comore nelloceano indiano flagellato costa settentrionale mozambicana venti 220 km orari radendo suolo interi villaggi portando piogge intensit\u00e0 torrenziale bilancio tuttavia avrebbe potuto essere peggiore se non fossero state sgomberate dalle abitazioni decine migliaia nellimminenza dellarrivo ciclone", "titolo_articolo": "mozambico 38 morti per ciclone kenneth", "tags": ["tempeste vento", "disastri; incidenti", "morte", "archiviato", "idai", "kenneth", "person"]}