{"categoria": "Cultura & Spettacoli", "sottotitolo": "furti falsi caccia dei carabinieri tesori salvare", "testo": "ansa   roma 22 apr   roberto riccardi detective dell arte rizzoli   pp 235   18 euro se non ci fosse stata l indagine nel 1998 mesi dal furto permise recuperare rimettere suo posto giardiniere van gogh oggi visitatore galleria nazionale d arte moderna roma troverebbe davanti parete bianca non fu grande risultato per cronaca giudiziaria conquista restituito mondo bene meraviglioso generale dei carabinieri roberto riccardi riassume cos\u00ec senso in 50 anni portato comando tutela patrimonio culturale livello eccellenza tutto mondo invidia all italia in mezzo secolo i segugi dell arma salvato centinaia migliaia beni dal piccolo crocifisso chiesa paese buccheri cocci saccheggiati dai tombaroli nelle necropoliai capolavori rubati in musei edifici pubblici abitazioni private all attivit\u00e0 silenziosa squadra specialisti fondata nel 1969 roberti settembre assumer\u00e0 guida comando dedica volume detective dell arte  pensato proprio per festeggiare compleanno particolare racconto furti clamorosi risolti come avvenne nel 1975 celebre quadro muta raffaello raffaello nel palazzo ducale urbino all opera maestro simbolo citt\u00e0 i ladri   italiani   portarono via piero francesca anno dopo vennero incastrati stratagemma ricettatore gi\u00e0 incassato prima rata per piazzare tele mercato internazionale dopo aver individuato persona ne era in possesso gli investigatori finsero collezionisti facoltosi intenzionati comprarle fissarono appuntamento in camera albergo locarno dove scattarono manette caso eclatante appunto rapina galleria nazionale d arte moderna roma dove i delinquenti armati bloccarono dipendenti rubarono vang gogh giardiniere l arlesiana cabanon de jourdan cezanne recuperati mesi dopo roma torino storia vicende lieto come nativit\u00e0 caravaggio rubata proprio 50 anni fa nell oratorio san lorenzo palermo quel capolavoro perdute tracce in scenario nel quale versioni contrastanti alcuni testimoni giustizia avrebbero giocato ruolo boss mafiosi i casi aperti   osserva riccardi   non chiudono mai all avanguardia i primi dotarci struttura genere nostra banca dati milione 300 mila files riferiti opere darte italiane paesi rubate disperse in guerre calamit\u00e0 naturali devastazioni saccheggi\u00a0\u00a0\u00a0 l attivit\u00e0 degli specialisti dell arma varcato i confini nazionali dal 2015 comando \u00e8 partner dell unesco iniziativa planetaria dei caschi blu cultura invenzione tutta italiana avviata miba$1$2un team 30 carabinieri 30 funzionari ministero assicura assistenza consulenza catalogazione tutela diretta dei beni culturali dei paesi devastati dai conflitti dai disastri naturali libro \u00e8 tuffo storia dell arte partire napoleone dopo campagna d italia port\u00f2 in francia cento capolavori in virt\u00f9 trattato tolentino fu l caso diritto saccheggio consentito vincitore\u00a0\u00a0\u00a0 opere finite in francia c era celebre gruppo laocoonte tornato in italia grazie grande scultore antonio canova nominato dal papa ambasciatore per recupero delle opere darte non cera gioconda era portato in francia leonardo poi venduto erede corte francesco i imbianchino veneto vincenzo peruggia rub\u00f2 nel 1911 infiltrandosi i dipendenti ditta pulizie louvre anni dopo l uomo present\u00f2 direttore degli uffizi dicendo l avrebbe consegnata patto restasse in italia non and\u00f2 cos\u00ec quadro torno suo posto fin\u00ec in galera\u00a0\u00a0\u00a0 capolavori rubati scomparsi distrutti storia falsi poteva mancare riferimento alle famigerata burla delle teste modigliani realizzate nel 1984 trapano elettrico ragazzi livorno ritrovate in canale citt\u00e0 rovinarono reputazione storici dell arte direttori musei titolati non fu l unico caso legato all artista livornese nel marzo 2017 quindicina presunti falsi maestro esposti in grande mostra palazzo dicale genova finiti centro inchiesta non conclusa caccia tesori rubati i carabinieri lavorano studiosi ricercatori archivisti in lotta contro rete spesso fanno parte delinquenti collezionisti galleristi direttori musei i ladri cultura   dice riccardi   ci rubano storia l identit\u00e0", "titolo_articolo": "i 50 anni dei detective dell arte", "tags": ["pittura", "arte; cultura; intrattenimento", "furti; rapine", "archiviato", "modigliani", "vincenzo peruggia", "francesco i", "vang gogh", "roberto riccardi", "luciano fioramonti", "paul c\u00e9zanne", "napoleone bonaparte", "caravaggio", "raffaello sanzio", "antonio canova", "piero della francesca", "vincent van gogh", "arlesiana", "leonardo", "person", "carabinieri", "unesco", "rizzoli", "roma", "torino", "organization"]}