{"categoria": "Mondo", "sottotitolo": "annuncia premier scott morrison", "testo": "ansa   canberra 11 apr   gli australiani andranno alle\nurne prossimo 18 maggio annunciato premier\naustraliano scott morrison \n   coalizione conservatrice morrison punta ad ottenere un\nterzo mandato triennale morrison \u00e8 ministro a\nguidare governo diviso sondaggi opinione suggeriscono che\nil suo regno   \u00e8 timone dellesecutivo dalla agosto  \ndiventer\u00e0 dei pi\u00f9 brevi storia 118 anni dei primi\nministri australiani\u00a0\u00a0\u00a0\n\t\t\t\t   favorito sondaggi \u00e8 leader dellopposizione di\ncentrosinistra bill shorten", "titolo_articolo": "australi$1$2si vota 18 maggio", "tags": ["voto", "governo nazionale", "sondaggio elettorale", "archiviato", "bill shorten", "scott morrison", "person"]}