{"categoria": "Cultura & Spettacoli", "sottotitolo": "14 dicembre bologna 15 milano shine light tour", "testo": "ansa   roma 11 mar   bryan adams annuncia tour mondiale shine light concerti in canada regno unito nuova zelanda australia europa non mancher\u00e0 litalia tappe bologna unipol arena 14 dicembre milano forum assago 15 dicembre\u00a0\u00a0\u00a0 bryan adams pubblicato suo album shine light marzo 2019 universal music group titolo dellalbum \u00e8 singolo punta disco \u00e8 scritto mani sheeran incontrato dublino questanno durante dei suoi concerti rimasti in contatto   detto adams   giorno gli mandato ritornello avevo per lidea canzone intitolata shine light gli chiesto se gli andasse collaborare ricevuto paio versi qualche giorno dopo cavolo dovreste sentirlo cantare questa canzone! nellalbum duetto jennifer lopez brano thats how strong our love is", "titolo_articolo": "bryan adams torna in italia per date", "tags": ["musica", "archiviato", "jennifer lopez", "ed sheeran", "bryan adams", "person", "universal music group", "organization"]}