{"categoria": "Cronaca", "sottotitolo": "ad jeh$1$2e prova visibile stiamo rispettando tutti gli impegni presi", "testo": "ultimati nel pieno dei tempi previsti dall\u2019addendum contratto affitto stipulato scorso settembre am investco italy lilva in amministrazione straordinaria fissava termine 30 aprile 2019 i lavori completamento 50% parte superiore struttura consentir\u00e0 copertura materiale presente nel parco minerale necessario fini livello produzione autorizzato arcelormittal nota spiega l\u2019attuale struttura composta moduli coperti dopo essere stata montata \u00e8 stata interamente spostata 230 metri in modo collocarla in maniera permanente cosiddetta posizione finale accanto quale prossimi mesi saranno agganciati i restanti moduli ad oggi inoltre \u00e8 in fase ultimazione modulo sar\u00e0 coperto sollevato collegato alcuni giorni\n\u00a0 \u00a0\u201cla realizzazione copertura dei parchi primari ossia parco minerali parco fossili \u2013 spiega l\u2019ad arcelormittal italia matthieu jehl \u2013 \u00e8 degli interventi pi\u00f9 importanti richiesti dallautorizzazione integrata ambientale risultato oggi \u00e8 prova visibile facciamo serio stiamo rispettando tutti gli impegni presi\u201d\ni lavori copertura dei parchi minerali affidati per progettazione fabbricazione montaggio ditta italiana cimolai   spiega societ\u00e0   iniziati posa prima pietra febbraio 2018 termineranno entro l\u2019ultimo trimestre 2019 copertura dei parchi primari volta completamente realizzata sar\u00e0 dei progetti ingegneristici ambientali pi\u00f9 ambiziosi mondo creer\u00e0 barriera fisica eviter\u00e0 dispersione delle polveri provenienti dai cumuli dei parchi citt\u00e0 in particolare quartiere tamburi in occasione dei cosiddetti wind days parte copertura sta realizzando pi\u00f9 rapidamente \u00e8 infatti quella trova maggiormente vicina quartiere", "titolo_articolo": "ex ilv$1$2arcelormittal completa copertura met\u00e0 parco minerale", "tags": []}