{"categoria": "Tecnologia", "sottotitolo": "", "testo": "worldwide developers conference apple avr\u00e0 inizio 4 giugno san jose svolger\u00e0 all\u20198 giugno mcenery convention center ospiter\u00e0 folta comunit\u00e0 sviluppatori riuniscono ogni anno per scoprire futuro prodotti servizi apple ogni anno wwdc offre milioni sviluppatori l\u2019opportunit\u00e0 approfondire i concetti i processi consentono creare nuove esperienze sulle piattaforme apple per iphone ipad apple watch apple tv mac homepod grazie gamma api sirikit homekit healthkit gymkit musickit researchkit core ml gli sviluppatori possono trovare modi per aiutare gli utenti gestire tutto dalla salute casa dallo shopping all\u2019apprendimento\nfino alle 10:00\u00a0pdt 22 marzo sito web wwdc https://developerapplecom/wwdc/register gli sviluppatori possono richiesta dei biglietti verranno assegnati partecipanti attraverso selezione casuale gli sviluppatori saranno informati sull\u2019esito richiesta entro 17:00 pdt 23 marzo\u00a0\nquest\u2019anno saranno disponibili 350 borse studio wwdc offrendo cos\u00ec studenti membri delle organizzazioni stem l\u2019opportunit\u00e0 ricevere biglietto gratuito i dettagli per candidatura degli studenti disponibili sito web wwdc developerapplecom/wwdc/scholarships", "titolo_articolo": "apple appuntamento gli sviluppatori", "tags": []}