{"categoria": "Sport", "sottotitolo": "centrocampista prossimo juventino infortunio ginocchio", "testo": "aaron ramsey centrocampista inglese dellarsenal prossimo anno giochera per juventus chiuso in anticipo sua stagione in premier league tecnico dei gunners unai emery annunciato vigilia semifinale andata europa league in casa col valencia ramsey soffre infortunio ginocchio non recuperera in per 29 maggio detto tecnico riferendosi data finale coppa europea quale sua squadra ambisce campionato inglese termina 12 maggio", "titolo_articolo": "arsenal stagione finita per ramsey", "tags": ["calcio", "archiviato", "aaron ramsey", "person", "uefa", "ansa", "associated press", "juventus", "roma", "premier league", "organization"]}