{"categoria": "Politica", "sottotitolo": "Sulla prevenzione idrica ancora oggi non \u00e8 stato fatto molto", "testo": "(ANSA) - MILANO, 03 NOV - \"Questo nostro incontro avviene 49\nanni e 364 giorni dopo un terribile evento, l'alluvione di\nFirenze\". Lo ha ricordato il premier Matteo Renzi intervenendo\nal Politecnico di Milano ad un confronto con gli studenti di\ningegneria e architettura dedicato al progetto Casa Italia,\ndedicato alla messa in sicurezza del Paese. \n   \"Allora accadde una reazione bellissima, quella degli angeli\ndel fango - ha concluso -. Ma ancora oggi sulla prevenzione\nidrica non e' stato fatto molto\". (ANSA).", "titolo_articolo": "A Milano Renzi ricorda alluvione di Firenze di 50 anni fa", "tags": []}