{"categoria": "Mondo", "sottotitolo": "'Legami tra Italia e Francia storicamente forti e profondi'", "testo": "(ANSA) - AMBOISE (FRANCIA), 2 MAG - \"Se abbiamo fatto la pace\ntra Italia e Francia? Non ce n'\u00e8 bisogno, i legami sono talmente\nforti, storicamente profondi che non ce n'era bisogno\": lo ha\ndetto il presidente della Repubblica Sergio Mattarella\nrispondendo a una domanda dei giornalisti dopo la visita alla\ncasa di Leonardo ad Amboise, la Clos Luc\u00e9, al fianco del\npresidente francese, Emmanuel Macron.", "titolo_articolo": "Mattarella da Macron,non serve fare pace", "tags": ["politica", "archiviato", "emmanuel macron", "sergio mattarella", "leonardo", "person"]}