{"categoria": "NULL", "sottotitolo": "UILPA", "testo": "Ascend Performance Materials announced today a price increase for all \r\n      grades of its FlexaTram\u2122- HMT (hexamethylenetetramine; \r\n      hexamine).\r\n    \r\n    \r\n\r\n      The price increase will take effect June 1, 2019, and includes the \r\n      following materials and terms:\r\n    \r\n    \r\n\r\n      \r\n\r\n        \r\n\r\n          Material\r\n        \r\n        \r\n          \u00a0\r\n        \r\n        \r\n          Price Increase\r\n        \r\n        \r\n          \u00a0\r\n        \r\n        \r\n          Terms\r\n        \r\n      \r\n\r\n      \r\n\r\n        \r\n\r\n          FlexaTram\u2122- HMT-200\r\n\r\n          \r\n            (aqueous solution)\r\n          \r\n        \r\n\r\n        \r\n          \u00a0\r\n        \r\n        \r\n          $0.04/lb.\r\n\r\n          \r\n            ($0.10/lb. on dry basis)\r\n          \r\n        \r\n\r\n        \r\n          \u00a0\r\n        \r\n        \r\n          \r\n\r\n            \r\n\r\n              As contracts allow.\r\n            \r\n            \r\n\r\n              Non-contract business \u2013 price determined on an order-by-order \r\n              basis.\r\n            \r\n          \r\n\r\n        \r\n\r\n      \r\n\r\n    \r\n\r\n    \r\n\r\n      Customers should contact their local sales representative for additional \r\n      information.\r\n    \r\n    \r\n\r\n      \r\nAbout Ascend Performance Materials\r\n    \r\n\r\n    \r\n\r\n      Ascend Performance Materials is a global premium provider of \r\n      high-quality plastics, fibers and chemicals and is the world\u2019s largest \r\n      integrated producer of PA66 resin. Headquartered in Houston, Texas, \r\n      Ascend has nine global locations, including five fully-integrated \r\n      manufacturing facilities located in the southeastern United States and \r\n      an engineering plastics compounding facility in Europe, all dedicated to \r\n      the innovation and safe production of nylon 6,6. With three of the \r\n      world\u2019s largest chemical processing facilities, Ascend\u2019s materials form \r\n      the building blocks for products used in everyday applications from \r\n      apparel to airbags, cable ties to circuit boards and carpets to car \r\n      parts. Ascend\u2019s 2,600-person global workforce is committed to making a \r\n      difference in the communities we serve and leading the development of \r\n      nylon 6,6 solutions that inspire everyone, everywhere, every day.\r\n    \r\n    \r\n\r\n      Together, we\u2019re making a difference.Together, we\u2019re inspiring \r\n      everyday.\r\n    \r\n    \r\n\r\n      More information about Ascend can be found at www.ascendmaterials.com\r\n    \r\n\r\n    \r\n\r\n    \r\n\r\n  \r\n\r\n\r\n\r\n\r\nView source version on businesswire.com: https://www.businesswire.com/news/home/20190502005633/en/\r\n\r\n    \r\n\r\n      Alison Jahn, +1 713-210-9809, ajahn@ascendmaterials.com\r\n    \r\n\r\n  \r\n\r\nPermalink: http://www.businesswire.com/news/home/20190502005633/en", "titolo_articolo": "Ascend Performance Materials Announces Price Increase for FlexaTram\u2122- HMT", "tags": []}