{"categoria": "Moto", "sottotitolo": "Pilota marchigiano bissa il successo del Qatar", "testo": "Lorenzo Baldassarri ha bissato in Argentina la vittoria conquistata in Qatar ed il pilota marchigiano \u00e8 a punteggio pieno, in testa alla classifica del mondiale Moto2. Sul podio sono saliti anche l'australiano Remy Gardner (prima volta in carriera) e lo spagnolo Alex Marquez.\u00a0\u00a0\u00a0 Settimo posto per Luca Marini, nono per Enea Bastianini.", "titolo_articolo": "Gp Argentina: Baldassarri vince in Moto2", "tags": ["sport", "archiviato", "enea bastianini", "luca marini", "alex marquez", "remy gardner", "lorenzo baldassarri", "person"]}