{"categoria": "Cultura & Spettacoli", "sottotitolo": "Il 28 giugno a Lucca, il 29 a Roma. A novembre esce Odissey", "titolo_articolo": "Take that in Italia con 2 date", "testo": "(ANSA) - FIRENZE, 21 SET - Doppia data italiana, il prossimo anno, per i Take That: nel tour internazionale per i 30 anni di attivit\u00e0, la celebre boy band si fermer\u00e0 in Italia per due concerti, il primo il 28 di giugno a Lucca in piazza Napoleone per il Summer Festival e il 29 a Roma, nella Cavea dell'Auditorium Parco della Musica di Roma. Proprio per celebrare le tre decadi di musica della formazione britannica, il prossimo novembre uscir\u00e0 Odissey, raccolta antologica con 27 brani che racconteranno in note i Take That dal loro debutto discografico nel 1992 ad oggi.", "tags": []}